llama_index/llms/pipeshift/__init__.py
llama_index/llms/pipeshift/base.py
llama_index_llms_pipeshift-0.3.1.dist-info/METADATA
llama_index_llms_pipeshift-0.3.1.dist-info/WHEEL
llama_index_llms_pipeshift-0.3.1.dist-info/licenses/LICENSE
llama_index_llms_pipeshift-0.3.1.dist-info/RECORD
